pdc/__init__.py
pdc/cli.py
pdc/core.py
pdc/reports.py
python_dependency_cleaner-0.1.1.dist-info/licenses/LICENSE
python_dependency_cleaner-0.1.1.dist-info/METADATA
python_dependency_cleaner-0.1.1.dist-info/WHEEL
python_dependency_cleaner-0.1.1.dist-info/entry_points.txt
python_dependency_cleaner-0.1.1.dist-info/top_level.txt
python_dependency_cleaner-0.1.1.dist-info/RECORD
