Metadata-Version: 2.4
Name: python-dependency-cleaner
Version: 0.1.1
Summary: A tool to analyze and clean unused Python dependencies
Author: Dor Mor
License: MIT
License-File: LICENSE
Dynamic: license-file
